itshire/__init__.py
itshire/__main__.py
itshire/add_frontmatter.py
itshire/add_sections.py
itshire/cli.py
itshire/log.py
itshire/main2.py
itshire/templates/base.j2
itshire/templates/extended.j2
itshire-0.1.26.dist-info/METADATA
itshire-0.1.26.dist-info/WHEEL
itshire-0.1.26.dist-info/entry_points.txt
itshire-0.1.26.dist-info/RECORD
