Metadata-Version: 2.4
Name: itshire
Version: 0.1.26
Summary: Add your description here
Author-email: Taylor Monacelli <taylormonacelli@gmail.com>
Requires-Python: >=3.8
Requires-Dist: jinja2>=3.1.3
Requires-Dist: mistletoe>=1.3.0
Requires-Dist: python-frontmatter>=1.1.0
